pyrodeo/__init__.py
pyrodeo/claw_solver.py
pyrodeo/coords.py
pyrodeo/hydro.py
pyrodeo/linear_advection.py
pyrodeo/param.py
pyrodeo/roe.py
pyrodeo/simulation.py
pyrodeo/state.py
pyrodeo/tests/__init__.py
pyrodeo/tests/test_cartesian.py
pyrodeo/tests/test_cyl.py
pyrodeo/tests/test_linear_advection.py
pyrodeo/tests/test_sheet.py
pyrodeo/tests/test_sph.py
pyrodeo-0.0.9.dist-info/METADATA
pyrodeo-0.0.9.dist-info/RECORD
pyrodeo-0.0.9.dist-info/WHEEL
pyrodeo-0.0.9.dist-info/top_level.txt
