Metadata-Version: 2.1
Name: pyrodeo
Version: 0.0.9
Summary: Isothermal disc hydrodynamics with a Roe solver
Home-page: https://github.com/SijmeJan/pyrodeo
Author: Sijme-Jan Paardekooper
License: UNKNOWN
Keywords: hydrodynamics disc planet
Platform: UNKNOWN
Classifier: Development Status :: 3 - Alpha
Classifier: Intended Audience :: Education
Classifier: Topic :: Scientific/Engineering :: Physics
Classifier: License :: OSI Approved :: GNU General Public License (GPL)
Classifier: Programming Language :: Python :: 3
Classifier: Programming Language :: Python :: 3.4
Classifier: Programming Language :: Python :: 3.5
Classifier: Programming Language :: Python :: 3.6
Requires-Dist: h5py
Requires-Dist: numpy
